iflow/__init__.py
iflow/api.py
iflow/auth.py
iflow/cli.py
iflow/config.py
iflow/curl.py
iflow/commands/__init__.py
iflow/commands/auth.py
iflow/commands/config.py
iflow/commands/files.py
iflow/commands/orders.py
iflow/commands/pipelines.py
iflow/commands/runs.py
intelliseq_iflow-0.2.9.dist-info/METADATA
intelliseq_iflow-0.2.9.dist-info/WHEEL
intelliseq_iflow-0.2.9.dist-info/entry_points.txt
intelliseq_iflow-0.2.9.dist-info/RECORD
